setup.py
obsoper/__init__.py
obsoper/bilinear.py
obsoper/box.c
obsoper/cell.c
obsoper/coordinates.py
obsoper/core.py
obsoper/cursors.c
obsoper/domain.py
obsoper/exceptions.py
obsoper/grid.py
obsoper/horizontal.py
obsoper/orca.py
obsoper/spherical.c
obsoper/version.py
obsoper/vertical.py
obsoper/walk.c
obsoper/window.py
obsoper.egg-info/PKG-INFO
obsoper.egg-info/SOURCES.txt
obsoper.egg-info/dependency_links.txt
obsoper.egg-info/top_level.txt
obsoper/test/__init__.py
obsoper/test/test_bilinear.py
obsoper/test/test_box.py
obsoper/test/test_cell.py
obsoper/test/test_coordinates.py
obsoper/test/test_cursors.py
obsoper/test/test_domain.py
obsoper/test/test_grid.py
obsoper/test/test_horizontal.py
obsoper/test/test_obsoper.py
obsoper/test/test_orca.py
obsoper/test/test_point_in_polygon.py
obsoper/test/test_public.py
obsoper/test/test_spherical.py
obsoper/test/test_version.py
obsoper/test/test_vertical.py
obsoper/test/test_walk.py
obsoper/test/test_window.py
obsoper/test/data/orca025_grid.nc