Metadata-Version: 1.0
Name: obsoper
Version: 0.0.7
Summary: observation operator
Home-page: https://github.com/met-office-ocean/obsoper
Author: Andrew Ryan
Author-email: andrew.ryan@metoffice.gov.uk
License: UNKNOWN
Platform: UNKNOWN
